PyQt5/QtScript.pyd
PyQt5/QtScriptTools.pyd
PyQt5/Qt/bin/Qt5Script.dll
PyQt5/Qt/bin/Qt5ScriptTools.dll
PyQtScript-5.13.1.20.dist-info/INSTALLER
PyQtScript-5.13.1.20.dist-info/METADATA
PyQtScript-5.13.1.20.dist-info/RECORD
